MANIFEST.in
README.txt
setup.py
docs/HISTORY.txt
src/silva/__init__.py
src/silva.app.page.egg-info/PKG-INFO
src/silva.app.page.egg-info/SOURCES.txt
src/silva.app.page.egg-info/dependency_links.txt
src/silva.app.page.egg-info/namespace_packages.txt
src/silva.app.page.egg-info/not-zip-safe
src/silva.app.page.egg-info/requires.txt
src/silva.app.page.egg-info/top_level.txt
src/silva/app/__init__.py
src/silva/app/page/__init__.py
src/silva/app/page/configure.zcml
src/silva/app/page/ftesting.zcml
src/silva/app/page/interfaces.py
src/silva/app/page/page.png
src/silva/app/page/page.py
src/silva/app/page/testing.py
src/silva/app/page/news/__init__.py
src/silva/app/page/news/agenda.png
src/silva/app/page/news/agenda.py
src/silva/app/page/news/blocks.py
src/silva/app/page/news/interfaces.py
src/silva/app/page/news/news.png
src/silva/app/page/news/news.py
src/silva/app/page/news/templates/agendainfo.cpt
src/silva/app/page/news/templates/newsinfo.cpt
src/silva/app/page/silvaxml/__init__.py
src/silva/app/page/silvaxml/xmlexport.py
src/silva/app/page/silvaxml/xmlimport.py
src/silva/app/page/static/pa-edit-styles.css
src/silva/app/page/tests/__init__.py
src/silva/app/page/tests/test_news.py
src/silva/app/page/tests/test_page.py
src/silva/app/page/tests/test_xml_export.py
src/silva/app/page/tests/test_xml_import.py
src/silva/app/page/tests/data/test_export_agenda_page.silvaxml
src/silva/app/page/tests/data/test_export_news_page.silvaxml
src/silva/app/page/tests/data/test_export_page.silvaxml
src/silva/app/page/tests/data/test_export_page_with_external_page_model.silvaxml
src/silva/app/page/tests/data/test_export_page_with_page_model.silvaxml
src/silva/app/page/tests/data/test_import_agenda_page.silvaxml
src/silva/app/page/tests/data/test_import_news_page.silvaxml
src/silva/app/page/tests/data/test_import_page.silvaxml
src/silva/app/page/tests/data/test_import_page_with_external_page_model.silvaxml
src/silva/app/page/tests/data/test_import_page_with_page_model.silvaxml