Metadata-Version: 1.1
Name: silva.app.page
Version: 3.0.4
Summary: Silva page content types for Silva CMS
Home-page: https://github.com/silvacms/silva.app.page
Author: Infrae
Author-email: info@infrae.com
License: GPL
Keywords: silva contentlayout zope cms
Platform: UNKNOWN
Classifier: Environment :: Web Environment
Classifier: Programming Language :: Python
Classifier: Topic :: Software Development :: Libraries :: Python Modules
Classifier: Framework :: Zope2
